Barcable/__init__.py
Barcable/_client/attributes.py
Barcable/_client/client.py
Barcable/_client/constants.py
Barcable/_client/datasets.py
Barcable/_client/environment_variables.py
Barcable/_client/get_client.py
Barcable/_client/observe.py
Barcable/_client/resource_manager.py
Barcable/_client/span.py
Barcable/_client/span_processor.py
Barcable/_client/utils.py
Barcable/_task_manager/media_manager.py
Barcable/_task_manager/media_upload_consumer.py
Barcable/_task_manager/media_upload_queue.py
Barcable/_task_manager/score_ingestion_consumer.py
Barcable/_utils/__init__.py
Barcable/_utils/environment.py
Barcable/_utils/error_logging.py
Barcable/_utils/parse_error.py
Barcable/_utils/prompt_cache.py
Barcable/_utils/request.py
Barcable/_utils/serializer.py
Barcable/api/README.md
Barcable/api/__init__.py
Barcable/api/client.py
Barcable/api/core/__init__.py
Barcable/api/core/api_error.py
Barcable/api/core/client_wrapper.py
Barcable/api/core/datetime_utils.py
Barcable/api/core/file.py
Barcable/api/core/http_client.py
Barcable/api/core/jsonable_encoder.py
Barcable/api/core/pydantic_utilities.py
Barcable/api/core/query_encoder.py
Barcable/api/core/remove_none_from_dict.py
Barcable/api/core/request_options.py
Barcable/api/reference.md
Barcable/api/resources/__init__.py
Barcable/api/resources/annotation_queues/__init__.py
Barcable/api/resources/annotation_queues/client.py
Barcable/api/resources/annotation_queues/types/__init__.py
Barcable/api/resources/annotation_queues/types/annotation_queue.py
Barcable/api/resources/annotation_queues/types/annotation_queue_assignment_request.py
Barcable/api/resources/annotation_queues/types/annotation_queue_item.py
Barcable/api/resources/annotation_queues/types/annotation_queue_object_type.py
Barcable/api/resources/annotation_queues/types/annotation_queue_status.py
Barcable/api/resources/annotation_queues/types/create_annotation_queue_assignment_response.py
Barcable/api/resources/annotation_queues/types/create_annotation_queue_item_request.py
barcable-3.4.2.dist-info/METADATA
barcable-3.4.2.dist-info/WHEEL
barcable-3.4.2.dist-info/entry_points.txt
barcable-3.4.2.dist-info/RECORD
